{
  "across": {
    "1": {
      "clue": "As filhas das filhas",
      "answer": "NETAS",
      "row": 0,
      "col": 0
    },
    "6": {
      "clue": "(Ingl.) Um acessório de cozinha",
      "answer": "GRILL",
      "row": 0,
      "col": 6
    },
    "10": {
      "clue": "Um Estado como o Qatar",
      "answer": "EMIRADO",
      "row": 1,
      "col": 0
    },
    "12": {
      "clue": "Em espanhol é calle",
      "answer": "RUA",
      "row": 1,
      "col": 8
    },
    "13": {
      "clue": "Unidade de Pronto Atendimento",
      "answer": "UPA",
      "row": 2,
      "col": 0
    },
    "14": {
      "clue": "A Gil apresentadora e culinarista",
      "answer": "BELA",
      "row": 2,
      "col": 4
    },
    "16": {
      "clue": "(Quím.) O tecnécio",
      "answer": "TC",
      "row": 2,
      "col": 9
    },
    "17": {
      "clue": "Renato Aragão, ator e humorista",
      "answer": "RA",
      "row": 3,
      "col": 0
    },
    "18": {
      "clue": "Variedade de uva vinífera",
      "answer": "CABERNET",
      "row": 3,
      "col": 3
    },
    "20": {
      "clue": "A capital da Turquia",
      "answer": "ANCARA",
      "row": 4,
      "col": 0
    },
    "22": {
      "clue": "Rija",
      "answer": "DURA",
      "row": 4,
      "col": 7
    },
    "23": {
      "clue": "Uma aranha europeia",
      "answer": "TARANTULA",
      "row": 5,
      "col": 1
    },
    "25": {
      "clue": "Impróprio, inadequado",
      "answer": "RUIM",
      "row": 6,
      "col": 0
    },
    "26": {
      "clue": "O aeronauta Alberto Santos (1873-1932)",
      "answer": "DUMONT",
      "row": 6,
      "col": 5
    },
    "28": {
      "clue": "Pontos que põem fim ao trabalho de uma costura",
      "answer": "ARREMATE",
      "row": 7,
      "col": 0
    },
    "30": {
      "clue": "Instituto Oceanográfico",
      "answer": "IO",
      "row": 7,
      "col": 9
    },
    "31": {
      "clue": "Samuel Rosa, músico, ex-\"Skank\"",
      "answer": "SR",
      "row": 8,
      "col": 0
    },
    "32": {
      "clue": "Atividade que pode ser praticada de peito",
      "answer": "NADO",
      "row": 8,
      "col": 3
    },
    "33": {
      "clue": "Lei de Segurança Nacional",
      "answer": "LSN",
      "row": 8,
      "col": 8
    },
    "34": {
      "clue": "(Esp.) Resistência física",
      "answer": "GAS",
      "row": 9,
      "col": 0
    },
    "36": {
      "clue": "Grande quantidade de peixes",
      "answer": "CARDUME",
      "row": 9,
      "col": 4
    },
    "38": {
      "clue": "Uma divindade no candomblé",
      "answer": "ORIXA",
      "row": 10,
      "col": 0
    },
    "39": {
      "clue": "Gancho usado para apanhar peixes",
      "answer": "ANZOL",
      "row": 10,
      "col": 6
    }
  },
  "down": {
    "1": {
      "clue": "(Pop.) Irritabilidade fácil",
      "answer": "NEURA",
      "row": 0,
      "col": 0
    },
    "2": {
      "clue": "Encher de comida",
      "answer": "EMPANTURRAR",
      "row": 0,
      "col": 1
    },
    "3": {
      "clue": "A mãe dos primos",
      "answer": "TIA",
      "row": 0,
      "col": 2
    },
    "4": {
      "clue": "Substância que enche balões",
      "answer": "AR",
      "row": 0,
      "col": 3
    },
    "5": {
      "clue": "Cidade histórica mineira",
      "answer": "SABARA",
      "row": 0,
      "col": 4
    },
    "6": {
      "clue": "Uma quantidade de líquido bebido",
      "answer": "GOLE",
      "row": 0,
      "col": 6
    },
    "7": {
      "clue": "Tomar determinado caminho",
      "answer": "IR",
      "row": 0,
      "col": 8
    },
    "8": {
      "clue": "A doutrina religiosa que deu origem à Reforma, na Alemanha",
      "answer": "LUTERANISMO",
      "row": 0,
      "col": 9
    },
    "9": {
      "clue": "A indústria que fabrica o \"Sonho de Valsa\"",
      "answer": "LACTA",
      "row": 0,
      "col": 10
    },
    "11": {
      "clue": "Correria, dispersão",
      "answer": "DEBANDADA",
      "row": 1,
      "col": 5
    },
    "15": {
      "clue": "Sabor picante",
      "answer": "ARDUME",
      "row": 2,
      "col": 7
    },
    "18": {
      "clue": "A Miranda (1909-1955) atriz e cantora",
      "answer": "CARMEN",
      "row": 3,
      "col": 3
    },
    "19": {
      "clue": "Em matemática, que tem o valor de zero",
      "answer": "NULO",
      "row": 3,
      "col": 8
    },
    "21": {
      "clue": "Vir abaixo",
      "answer": "CAIR",
      "row": 4,
      "col": 2
    },
    "24": {
      "clue": "Aquela que protege",
      "answer": "TUTORA",
      "row": 5,
      "col": 6
    },
    "25": {
      "clue": "Fenda",
      "answer": "RASGO",
      "row": 6,
      "col": 0
    },
    "27": {
      "clue": "Barril de 840 litros",
      "answer": "TONEL",
      "row": 6,
      "col": 10
    },
    "29": {
      "clue": "Pequena cama para transportar atleta lesionado",
      "answer": "MACA",
      "row": 7,
      "col": 4
    },
    "33": {
      "clue": "A artificial não provém do Sol",
      "answer": "LUZ",
      "row": 8,
      "col": 8
    },
    "35": {
      "clue": "A última nota da escala diatônica",
      "answer": "SI",
      "row": 9,
      "col": 2
    },
    "37": {
      "clue": "Diogo Nogueira, sambista",
      "answer": "DN",
      "row": 9,
      "col": 7
    }
  }
}